pretix_sumup/__init__.py
pretix_sumup/apps.py
pretix_sumup/payment.py
pretix_sumup/signals.py
pretix_sumup/sumup_client.py
pretix_sumup/urls.py
pretix_sumup/views.py
pretix_sumup/locale/de/LC_MESSAGES/django.mo
pretix_sumup/locale/de/LC_MESSAGES/django.po
pretix_sumup/locale/de_Informal/.gitkeep
pretix_sumup/locale/de_Informal/LC_MESSAGES/django.mo
pretix_sumup/locale/de_Informal/LC_MESSAGES/django.po
pretix_sumup/static/pretix_sumup/.gitkeep
pretix_sumup/templates/pretix_sumup/control.html
pretix_sumup/templates/pretix_sumup/payment_widget.html
pretix_sumup_payment_plus-1.1.9.dist-info/licenses/LICENSE
pretix_sumup_payment_plus-1.1.9.dist-info/METADATA
pretix_sumup_payment_plus-1.1.9.dist-info/WHEEL
pretix_sumup_payment_plus-1.1.9.dist-info/entry_points.txt
pretix_sumup_payment_plus-1.1.9.dist-info/top_level.txt
pretix_sumup_payment_plus-1.1.9.dist-info/RECORD
