Metadata-Version: 2.4
Name: pretix-sumup-payment-plus
Version: 1.1.9
Summary: Enables credit card payments via SumUp
Author-email: Christoph Walcher <chris@wiomoc.de>, Botond Moksony <botond@moksony.com>
Maintainer-email: Christoph Walcher <chris@wiomoc.de>
License: Apache
Project-URL: homepage, https://github.com/wiomoc/pretix-sumup-payment
Project-URL: repository, https://github.com/wiomoc/pretix-sumup-payment
Keywords: pretix
License-File: LICENSE
Dynamic: license-file
